{"STATUSTEXT": {"mavpackettype": "STATUSTEXT", "severity": 6, "text": "AHRS: EKF3 active", "id": 0, "chunk_seq": 0}, "HEARTBEAT": {"mavpackettype": "HEARTBEAT", "type": 2, "autopilot": 3, "base_mode": 89, "custom_mode": 6, "system_status": 3, "mavlink_version": 3}, "ATTITUDE": {"mavpackettype": "ATTITUDE", "time_boot_ms": 9813, "roll": 0.05521710589528084, "pitch": 0.021557148545980453, "yaw": -0.00027548798243515193, "rollspeed": -0.0006767451413907111, "pitchspeed": -0.0014338336186483502, "yawspeed": 0.0007654328364878893}, "GLOBAL_POSITION_INT": {"mavpackettype": "GLOBAL_POSITION_INT", "time_boot_ms": 9813, "lat": 548430956, "lon": 830985176, "alt": 520, "relative_alt": 982, "vx": -1, "vy": 0, "vz": 24, "hdg": 1}, "SYS_STATUS": {"mavpackettype": "SYS_STATUS", "onboard_control_sensors_present": 1399979055, "onboard_control_sensors_enabled": 1380056111, "onboard_control_sensors_health": 1196555279, "load": 459, "voltage_battery": 16319, "current_battery": 18, "battery_remaining": 99, "drop_rate_comm": 0, "errors_comm": 0, "errors_count1": 0, "errors_count2": 0, "errors_count3": 0, "errors_count4": 0}, "POWER_STATUS": {"mavpackettype": "POWER_STATUS", "Vcc": 4671, "Vservo": 4721, "flags": 0}, "MEMINFO": {"mavpackettype": "MEMINFO", "brkval": 0, "freemem": 50776, "freemem32": 50776}, "NAV_CONTROLLER_OUTPUT": {"mavpackettype": "NAV_CONTROLLER_OUTPUT", "nav_roll": 0.0, "nav_pitch": 0.0, "nav_bearing": 38, "target_bearing": 0, "wp_dist": 0, "alt_error": 0.2091120034456253, "aspd_error": 0.0, "xtrack_error": 0.0}, "MISSION_CURRENT": {"mavpackettype": "MISSION_CURRENT", "seq": 0, "total": 17, "mission_state": 2, "mission_mode": 0}, "VFR_HUD": {"mavpackettype": "VFR_HUD", "airspeed": 0.004399561323225498, "groundspeed": 0.014920063316822052, "heading": 0, "throttle": 0, "alt": 0.5199999809265137, "climb": -0.2429344207048416}, "SERVO_OUTPUT_RAW": {"mavpackettype": "SERVO_OUTPUT_RAW", "time_usec": 9816073, "port": 0, "servo1_raw": 1000, "servo2_raw": 1000, "servo3_raw": 1000, "servo4_raw": 1000, "servo5_raw": 0, "servo6_raw": 0, "servo7_raw": 0, "servo8_raw": 0, "servo9_raw": 0, "servo10_raw": 0, "servo11_raw": 0, "servo12_raw": 0, "servo13_raw": 0, "servo14_raw": 0, "servo15_raw": 0, "servo16_raw": 0}, "RC_CHANNELS": {"mavpackettype": "RC_CHANNELS", "time_boot_ms": 9690, "chancount": 16, "chan1_raw": 1497, "chan2_raw": 1496, "chan3_raw": 1541, "chan4_raw": 1493, "chan5_raw": 2006, "chan6_raw": 982, "chan7_raw": 1323, "chan8_raw": 1320, "chan9_raw": 2006, "chan10_raw": 982, "chan11_raw": 1495, "chan12_raw": 1495, "chan13_raw": 1495, "chan14_raw": 1495, "chan15_raw": 1495, "chan16_raw": 2006, "chan17_raw": 0, "chan18_raw": 0, "rssi": 255}, "RAW_IMU": {"mavpackettype": "RAW_IMU", "time_usec": 9690782, "xacc": 36, "yacc": -67, "zacc": -989, "xgyro": 0, "ygyro": 2, "zgyro": 0, "xmag": 85, "ymag": -46, "zmag": 606, "id": 0, "temperature": 1574}, "SCALED_IMU2": {"mavpackettype": "SCALED_IMU2", "time_boot_ms": 9693, "xacc": 39, "yacc": -63, "zacc": -1009, "xgyro": -1, "ygyro": 8, "zgyro": -1, "xmag": 469, "ymag": 537, "zmag": 628, "temperature": 1397}, "SCALED_PRESSURE": {"mavpackettype": "SCALED_PRESSURE", "time_boot_ms": 9695, "press_abs": 992.91357421875, "press_diff": 0.0, "temperature": 1053, "temperature_press_diff": 0}, "GPS_RAW_INT": {"mavpackettype": "GPS_RAW_INT", "time_usec": 9580000, "fix_type": 3, "lat": 548430956, "lon": 830985176, "alt": 370, "eph": 100, "epv": 100, "vel": 0, "cog": 27683, "satellites_visible": 10, "alt_ellipsoid": 0, "h_acc": 0, "v_acc": 0, "vel_acc": 600, "hdg_acc": 0, "yaw": 0}, "SYSTEM_TIME": {"mavpackettype": "SYSTEM_TIME", "time_unix_usec": 1734795053832675, "time_boot_ms": 9715}, "AHRS": {"mavpackettype": "AHRS", "omegaIx": -0.0, "omegaIy": -0.0, "omegaIz": -0.0, "accel_weight": 0.0, "renorm_val": 0.0, "error_rp": 0.01134080346673727, "error_yaw": 0.010941511020064354}, "TERRAIN_REPORT": {"mavpackettype": "TERRAIN_REPORT", "lat": 548430956, "lon": 830985176, "spacing": 100, "terrain_height": 169.38087463378906, "current_height": -168.86087036132812, "pending": 0, "loaded": 336}, "VIBRATION": {"mavpackettype": "VIBRATION", "time_usec": 9738804, "vibration_x": 0.021714022383093834, "vibration_y": 0.025661567226052284, "vibration_z": 0.029501520097255707, "clipping_0": 0, "clipping_1": 0, "clipping_2": 0}, "BATTERY_STATUS": {"mavpackettype": "BATTERY_STATUS", "id": 0, "battery_function": 0, "type": 0, "temperature": 32767, "voltages": [16322, 65535, 65535, 65535, 65535, 65535, 65535, 65535, 65535, 65535], "current_battery": 19, "current_consumed": 0, "energy_consumed": 0, "battery_remaining": 99, "time_remaining": 0, "charge_state": 1, "voltages_ext": [0, 0, 0, 0], "mode": 0, "fault_bitmask": 0}, "PARAM_VALUE": {"mavpackettype": "PARAM_VALUE", "param_id": "INS_GYR3OFFS_Z", "param_value": 0.0, "param_type": 9, "param_count": 1017, "param_index": 65535}, "COMMAND_ACK": {"mavpackettype": "COMMAND_ACK", "command": 410, "result": 4, "progress": 0, "result_param2": 0, "target_system": 255, "target_component": 230}, "EKF_STATUS_REPORT": {"mavpackettype": "EKF_STATUS_REPORT", "flags": 0, "velocity_variance": 0.0, "pos_horiz_variance": 0.0007622815319336951, "pos_vert_variance": 0.0492771677672863, "compass_variance": 0.0, "terrain_alt_variance": 0.0, "airspeed_variance": 0.0}, "AHRS2": {"mavpackettype": "AHRS2", "roll": 0.04517047107219696, "pitch": 0.02164752036333084, "yaw": 0.7739571332931519, "altitude": 0.8700000047683716, "lat": 548430956, "lng": 830985176}, "GNRMC": {"_immutable": true, "_logger": "", "_validate": 1, "_userdefined": {}, "_defsource": 0, "_mode": 0, "_hpnmeamode": false, "_talker": "GN", "_msgID": "RMC", "_payload": ["082655.10", "V", "", "", "", "", "", "", "151224", "", "", "N"], "_checksum": "6F", "time": "08:26:55.100000", "status": "V", "lat": "", "NS": "", "lon": "", "EW": "", "spd": "", "cog": "", "date": "15/12/2024", "mv": "", "mvEW": "", "posMode": "N"}, "GNVTG": {"_immutable": true, "_logger": "", "_validate": 1, "_userdefined": {}, "_defsource": 0, "_mode": 0, "_hpnmeamode": false, "_talker": "GN", "_msgID": "VTG", "_payload": ["", "", "", "", "", "", "", "", "N"], "_checksum": "2E", "cogt": "", "cogtUnit": "", "cogm": "", "cogmUnit": "", "sogn": "", "sognUnit": "", "sogk": "", "sogkUnit": "", "posMode": "N"}, "GNGGA": {"_immutable": true, "_logger": "", "_validate": 1, "_userdefined": {}, "_defsource": 0, "_mode": 0, "_hpnmeamode": false, "_talker": "GN", "_msgID": "GGA", "_payload": ["082655.10", "", "", "", "", "0", "00", "99.99", "", "", "", "", "", ""], "_checksum": "75", "time": "08:26:55.100000", "lat": "", "NS": "", "lon": "", "EW": "", "quality": 0, "numSV": 0, "HDOP": 99.99, "alt": "", "altUnit": "", "sep": "", "sepUnit": "", "diffAge": "", "diffStation": ""}, "GNGSA": {"_immutable": true, "_logger": "", "_validate": 1, "_userdefined": {}, "_defsource": 0, "_mode": 0, "_hpnmeamode": false, "_talker": "GN", "_msgID": "GSA", "_payload": ["A", "1", "", "", "", "", "", "", "", "", "", "", "", "", "99.99", "99.99", "99.99"], "_checksum": "2E", "opMode": "A", "navMode": 1, "svid_01": "", "svid_02": "", "svid_03": "", "svid_04": "", "svid_05": "", "svid_06": "", "svid_07": "", "svid_08": "", "svid_09": "", "svid_10": "", "svid_11": "", "svid_12": "", "PDOP": 99.99, "HDOP": 99.99, "VDOP": 99.99}, "GPGSV": {"_immutable": true, "_logger": "", "_validate": 1, "_userdefined": {}, "_defsource": 0, "_mode": 0, "_hpnmeamode": false, "_talker": "GP", "_msgID": "GSV", "_payload": ["3", "1", "09", "05", "", "", "33", "07", "", "", "32", "08", "", "", "39", "09", "", "", "36"], "_checksum": "7F", "numMsg": 3, "msgNum": 1, "numSV": 9, "svid_01": 5, "elv_01": "", "az_01": "", "cno_01": 33, "svid_02": 7, "elv_02": "", "az_02": "", "cno_02": 32, "svid_03": 8, "elv_03": "", "az_03": "", "cno_03": 39, "svid_04": 9, "elv_04": "", "az_04": "", "cno_04": 36}, "GLGSV": {"_immutable": true, "_logger": "", "_validate": 1, "_userdefined": {}, "_defsource": 0, "_mode": 0, "_hpnmeamode": false, "_talker": "GL", "_msgID": "GSV", "_payload": ["1", "1", "01", "", "", "", "31"], "_checksum": "66", "numMsg": 1, "msgNum": 1, "numSV": 1, "svid_01": "", "elv_01": "", "az_01": "", "cno_01": 31}, "GNGLL": {"_immutable": true, "_logger": "", "_validate": 1, "_userdefined": {}, "_defsource": 0, "_mode": 0, "_hpnmeamode": false, "_talker": "GN", "_msgID": "GLL", "_payload": ["", "", "", "", "082655.00", "V", "N"], "_checksum": "58", "lat": "", "NS": "", "lon": "", "EW": "", "time": "08:26:55.000000", "status": "V", "posMode": "N"}, "VIO": {"timestamp": 1734247872.082676, "to_north": -0.0011274715199386647, "to_east": -0.001631652629646309, "lat": 54.84309568268973, "lon": 83.09851768334902, "alt": 0.8700000047683716, "veln": 8.121503411192124e-05, "vele": -0.0004599894314009398, "veld": 0.0, "GPS_week": 2345, "GPS_ms": 574272222}}