{"HEARTBEAT": {"mavpackettype": "HEARTBEAT", "type": 2, "autopilot": 3, "base_mode": 217, "custom_mode": 5, "system_status": 4, "mavlink_version": 3}, "STATUSTEXT": {"mavpackettype": "STATUSTEXT", "severity": 6, "text": "EKF3 IMU0 MAG1 in-flight yaw alignment complete", "id": 0, "chunk_seq": 0}, "ATTITUDE": {"mavpackettype": "ATTITUDE", "time_boot_ms": 89578, "roll": -0.08567074686288834, "pitch": -0.01970558986067772, "yaw": 2.301776647567749, "rollspeed": 0.03821922838687897, "pitchspeed": -0.10766539722681046, "yawspeed": 0.08375773578882217}, "GLOBAL_POSITION_INT": {"mavpackettype": "GLOBAL_POSITION_INT", "time_boot_ms": 89578, "lat": 548471832, "lon": 831275391, "alt": 10820, "relative_alt": 10715, "vx": 14, "vy": 0, "vz": -27, "hdg": 22812}, "SYS_STATUS": {"mavpackettype": "SYS_STATUS", "onboard_control_sensors_present": 1399979055, "onboard_control_sensors_enabled": 1398930479, "onboard_control_sensors_health": 1467087919, "load": 542, "voltage_battery": 14479, "current_battery": 1299, "battery_remaining": 99, "drop_rate_comm": 0, "errors_comm": 0, "errors_count1": 0, "errors_count2": 0, "errors_count3": 0, "errors_count4": 0}, "POWER_STATUS": {"mavpackettype": "POWER_STATUS", "Vcc": 4832, "Vservo": 4922, "flags": 0}, "MEMINFO": {"mavpackettype": "MEMINFO", "brkval": 0, "freemem": 50288, "freemem32": 50288}, "NAV_CONTROLLER_OUTPUT": {"mavpackettype": "NAV_CONTROLLER_OUTPUT", "nav_roll": -5.0800604820251465, "nav_pitch": -1.3850529193878174, "nav_bearing": -130, "target_bearing": 291, "wp_dist": 0, "alt_error": 0.09019531309604645, "aspd_error": 0.0, "xtrack_error": 0.14368455111980438}, "MISSION_CURRENT": {"mavpackettype": "MISSION_CURRENT", "seq": 0, "total": 6, "mission_state": 2, "mission_mode": 0}, "VFR_HUD": {"mavpackettype": "VFR_HUD", "airspeed": 0.29660719633102417, "groundspeed": 0.13588464260101318, "heading": 227, "throttle": 26, "alt": 10.800000190734863, "climb": 0.26364976167678833}, "SERVO_OUTPUT_RAW": {"mavpackettype": "SERVO_OUTPUT_RAW", "time_usec": 89442323, "port": 0, "servo1_raw": 1564, "servo2_raw": 1547, "servo3_raw": 1404, "servo4_raw": 1516, "servo5_raw": 0, "servo6_raw": 0, "servo7_raw": 0, "servo8_raw": 0, "servo9_raw": 0, "servo10_raw": 0, "servo11_raw": 0, "servo12_raw": 0, "servo13_raw": 0, "servo14_raw": 0, "servo15_raw": 0, "servo16_raw": 0}, "RC_CHANNELS": {"mavpackettype": "RC_CHANNELS", "time_boot_ms": 89442, "chancount": 16, "chan1_raw": 1498, "chan2_raw": 1497, "chan3_raw": 1625, "chan4_raw": 1492, "chan5_raw": 1495, "chan6_raw": 982, "chan7_raw": 1321, "chan8_raw": 1318, "chan9_raw": 982, "chan10_raw": 982, "chan11_raw": 1495, "chan12_raw": 1495, "chan13_raw": 1495, "chan14_raw": 1495, "chan15_raw": 1495, "chan16_raw": 2006, "chan17_raw": 0, "chan18_raw": 0, "rssi": 255}, "RAW_IMU": {"mavpackettype": "RAW_IMU", "time_usec": 89444538, "xacc": -1, "yacc": 138, "zacc": -1035, "xgyro": 73, "ygyro": -165, "zgyro": 42, "xmag": 619, "ymag": -9, "zmag": 961, "id": 0, "temperature": 414}, "SCALED_IMU2": {"mavpackettype": "SCALED_IMU2", "time_boot_ms": 89444, "xacc": 0, "yacc": 0, "zacc": 0, "xgyro": 0, "ygyro": 0, "zgyro": 0, "xmag": -121, "ymag": 14, "zmag": 627, "temperature": 0}, "SCALED_IMU3": {"mavpackettype": "SCALED_IMU3", "time_boot_ms": 89449, "xacc": 0, "yacc": 0, "zacc": 0, "xgyro": 0, "ygyro": 0, "zgyro": 0, "xmag": 0, "ymag": 0, "zmag": 0, "temperature": 0}, "SCALED_PRESSURE": {"mavpackettype": "SCALED_PRESSURE", "time_boot_ms": 89450, "press_abs": 1013.9974975585938, "press_diff": 0.0, "temperature": -175, "temperature_press_diff": 0}, "GPS_RAW_INT": {"mavpackettype": "GPS_RAW_INT", "time_usec": 89378000, "fix_type": 3, "lat": 548471824, "lon": 831275394, "alt": 10400, "eph": 100, "epv": 100, "vel": 23, "cog": 7971, "satellites_visible": 10, "alt_ellipsoid": 0, "h_acc": 0, "v_acc": 0, "vel_acc": 600, "hdg_acc": 0, "yaw": 0}, "SYSTEM_TIME": {"mavpackettype": "SYSTEM_TIME", "time_unix_usec": 1734794351536290, "time_boot_ms": 89475}, "AHRS": {"mavpackettype": "AHRS", "omegaIx": -0.002092772163450718, "omegaIy": -0.001253455993719399, "omegaIz": -0.0004105092375539243, "accel_weight": 0.0, "renorm_val": 0.0, "error_rp": 0.20707538723945618, "error_yaw": 0.022175772115588188}, "TERRAIN_REPORT": {"mavpackettype": "TERRAIN_REPORT", "lat": 548471832, "lon": 831275389, "spacing": 100, "terrain_height": 166.17129516601562, "current_height": -155.36129760742188, "pending": 0, "loaded": 448}, "VIBRATION": {"mavpackettype": "VIBRATION", "time_usec": 89505310, "vibration_x": 2.990872859954834, "vibration_y": 5.624489784240723, "vibration_z": 2.2716104984283447, "clipping_0": 0, "clipping_1": 0, "clipping_2": 0}, "BATTERY_STATUS": {"mavpackettype": "BATTERY_STATUS", "id": 0, "battery_function": 0, "type": 0, "temperature": 32767, "voltages": [14478, 65535, 65535, 65535, 65535, 65535, 65535, 65535, 65535, 65535], "current_battery": 1317, "current_consumed": 57, "energy_consumed": 30, "battery_remaining": 99, "time_remaining": 0, "charge_state": 1, "voltages_ext": [0, 0, 0, 0], "mode": 0, "fault_bitmask": 0}, "PARAM_VALUE": {"mavpackettype": "PARAM_VALUE", "param_id": "BARO1_GND_PRESS", "param_value": 101533.6171875, "param_type": 9, "param_count": 1017, "param_index": 65535}, "COMMAND_ACK": {"mavpackettype": "COMMAND_ACK", "command": 410, "result": 4, "progress": 0, "result_param2": 0, "target_system": 255, "target_component": 230}, "EKF_STATUS_REPORT": {"mavpackettype": "EKF_STATUS_REPORT", "flags": 831, "velocity_variance": 0.03718096390366554, "pos_horiz_variance": 0.02254130318760872, "pos_vert_variance": 0.04090498387813568, "compass_variance": 0.01582426391541958, "terrain_alt_variance": 0.0, "airspeed_variance": 0.0}, "AHRS2": {"mavpackettype": "AHRS2", "roll": -0.09501000493764877, "pitch": -0.004035541322082281, "yaw": -2.3512308597564697, "altitude": 10.679999351501465, "lat": 548471825, "lng": 831275404}, "TIMESYNC": {"mavpackettype": "TIMESYNC", "tc1": 0, "ts1": 80017259001}, "GPS_GLOBAL_ORIGIN": {"mavpackettype": "GPS_GLOBAL_ORIGIN", "latitude": 548471833, "longitude": 831275374, "altitude": 0, "time_usec": 64798104}, "HOME_POSITION": {"mavpackettype": "HOME_POSITION", "latitude": 548471836, "longitude": 831275370, "altitude": 110, "x": 0.03339565545320511, "y": -0.02563714236021042, "z": -0.10999999940395355, "q": [NaN, NaN, NaN, NaN], "approach_x": 0.0, "approach_y": 0.0, "approach_z": 0.0, "time_usec": 64810547}, "WIND": {"mavpackettype": "WIND", "direction": -180.0, "speed": 0.0, "speed_z": 0.0}, "LOCAL_POSITION_NED": {"mavpackettype": "LOCAL_POSITION_NED", "time_boot_ms": 89498, "x": -0.007960313931107521, "y": 0.10209154337644577, "z": -10.812540054321289, "vx": 0.13567987084388733, "vy": 0.0017630679067224264, "vz": -0.2654997408390045}, "GNRMC": {"_immutable": true, "_logger": "", "_validate": 1, "_userdefined": {}, "_defsource": 0, "_mode": 0, "_hpnmeamode": false, "_talker": "GN", "_msgID": "RMC", "_payload": ["091601.50", "A", "5450.83017", "N", "08307.64956", "E", "0.317", "", "171224", "", "", "A"], "_checksum": "6F", "time": "09:16:01.500000", "status": "A", "lat": 54.8471695, "NS": "N", "lon": 83.1274926667, "EW": "E", "spd": 0.317, "cog": "", "date": "17/12/2024", "mv": "", "mvEW": "", "posMode": "A"}, "GNVTG": {"_immutable": true, "_logger": "", "_validate": 1, "_userdefined": {}, "_defsource": 0, "_mode": 0, "_hpnmeamode": false, "_talker": "GN", "_msgID": "VTG", "_payload": ["", "T", "", "M", "0.317", "N", "0.588", "K", "A"], "_checksum": "3D", "cogt": "", "cogtUnit": "T", "cogm": "", "cogmUnit": "M", "sogn": 0.317, "sognUnit": "N", "sogk": 0.588, "sogkUnit": "K", "posMode": "A"}, "GNGGA": {"_immutable": true, "_logger": "", "_validate": 1, "_userdefined": {}, "_defsource": 0, "_mode": 0, "_hpnmeamode": false, "_talker": "GN", "_msgID": "GGA", "_payload": ["091601.50", "5450.83017", "N", "08307.64956", "E", "1", "12", "0.71", "200.4", "M", "-38.2", "M", "", ""], "_checksum": "62", "time": "09:16:01.500000", "lat": 54.8471695, "NS": "N", "lon": 83.1274926667, "EW": "E", "quality": 1, "numSV": 12, "HDOP": 0.71, "alt": 200.4, "altUnit": "M", "sep": -38.2, "sepUnit": "M", "diffAge": "", "diffStation": ""}, "GNGSA": {"_immutable": true, "_logger": "", "_validate": 1, "_userdefined": {}, "_defsource": 0, "_mode": 0, "_hpnmeamode": false, "_talker": "GN", "_msgID": "GSA", "_payload": ["A", "3", "75", "66", "85", "67", "76", "65", "", "", "", "", "", "", "1.32", "0.71", "1.12"], "_checksum": "14", "opMode": "A", "navMode": 3, "svid_01": 75, "svid_02": 66, "svid_03": 85, "svid_04": 67, "svid_05": 76, "svid_06": 65, "svid_07": "", "svid_08": "", "svid_09": "", "svid_10": "", "svid_11": "", "svid_12": "", "PDOP": 1.32, "HDOP": 0.71, "VDOP": 1.12}, "GPGSV": {"_immutable": true, "_logger": "", "_validate": 1, "_userdefined": {}, "_defsource": 0, "_mode": 0, "_hpnmeamode": false, "_talker": "GP", "_msgID": "GSV", "_payload": ["3", "3", "12", "21", "23", "116", "30", "22", "19", "254", "31", "27", "23", "049", "36", "30", "71", "264", "33"], "_checksum": "7D", "numMsg": 3, "msgNum": 3, "numSV": 12, "svid_01": 21, "elv_01": 23.0, "az_01": 116, "cno_01": 30, "svid_02": 22, "elv_02": 19.0, "az_02": 254, "cno_02": 31, "svid_03": 27, "elv_03": 23.0, "az_03": 49, "cno_03": 36, "svid_04": 30, "elv_04": 71.0, "az_04": 264, "cno_04": 33}, "GLGSV": {"_immutable": true, "_logger": "", "_validate": 1, "_userdefined": {}, "_defsource": 0, "_mode": 0, "_hpnmeamode": false, "_talker": "GL", "_msgID": "GSV", "_payload": ["3", "3", "09", "85", "35", "132", "27"], "_checksum": "52", "numMsg": 3, "msgNum": 3, "numSV": 9, "svid_01": 85, "elv_01": 35.0, "az_01": 132, "cno_01": 27}, "GNGLL": {"_immutable": true, "_logger": "", "_validate": 1, "_userdefined": {}, "_defsource": 0, "_mode": 0, "_hpnmeamode": false, "_talker": "GN", "_msgID": "GLL", "_payload": ["5450.83013", "N", "08307.64953", "E", "091601.00", "A", "A"], "_checksum": "74", "lat": 54.8471688333, "NS": "N", "lon": 83.1274921667, "EW": "E", "time": "09:16:01.000000", "status": "A", "posMode": "A"}, "GNTXT": {"_immutable": true, "_logger": "", "_validate": 1, "_userdefined": {}, "_defsource": 0, "_mode": 0, "_hpnmeamode": false, "_talker": "GN", "_msgID": "TXT", "_payload": ["01", "01", "01", "More than 100 frame errors", " UART RX was disabled"], "_checksum": "70", "numMsg": 1, "msgNum": 1, "msgType": 1, "text": "More than 100 frame errors"}, "VIO": {"timestamp": 1734247169.757938, "to_north": -0.06333758773564743, "to_east": 0.24607689339791838, "lat": 54.84718276433137, "lon": 83.12754133934159, "alt": 10.679999351501465, "veln": 0.09864224541986184, "vele": 0.3151052391909148, "veld": 0.0, "GPS_week": 2345, "GPS_ms": 573569921}}